odoo/addons/vertical_carsharing_emc/__init__.py
odoo/addons/vertical_carsharing_emc/__manifest__.py
odoo/addons/vertical_carsharing_emc/listeners/__init__.py
odoo/addons/vertical_carsharing_emc/listeners/subscription_request.py
odoo/addons/vertical_carsharing_emc/models/__init__.py
odoo/addons/vertical_carsharing_emc/models/models_sm_company.py
odoo/addons/vertical_carsharing_emc/models/models_smp_carsharing_registration_request.py
odoo/addons/vertical_carsharing_emc/models/models_subscription_request.py
odoo/addons/vertical_carsharing_emc/services/__init__.py
odoo/addons/vertical_carsharing_emc/services/schemas.py
odoo/addons/vertical_carsharing_emc/services/services_cs_registration_request.py
odoo/addons/vertical_carsharing_emc/services/services_subscription_request.py
odoo/addons/vertical_carsharing_emc/views/views_cron.xml
odoo/addons/vertical_carsharing_emc/views/views_cs_registration_request.xml
odoo/addons/vertical_carsharing_emc/views/views_res_company.xml
odoo/addons/vertical_carsharing_emc/views/views_subscription_request.xml
odoo12_addon_vertical_carsharing_emc-12.0.0.0.18.dist-info/METADATA
odoo12_addon_vertical_carsharing_emc-12.0.0.0.18.dist-info/WHEEL
odoo12_addon_vertical_carsharing_emc-12.0.0.0.18.dist-info/top_level.txt
odoo12_addon_vertical_carsharing_emc-12.0.0.0.18.dist-info/RECORD
